subsys_counter/__init__.py
subsys_counter-0.8.5.dist-info/METADATA
subsys_counter-0.8.5.dist-info/WHEEL
subsys_counter-0.8.5.dist-info/top_level.txt
subsys_counter-0.8.5.dist-info/RECORD
