Metadata-Version: 2.1
Name: subsys-counter
Version: 0.8.5
Summary: test
Author: serverinspector2
Author-email: serverinspector+2@wearehackerone.com
Requires-Dist: requests
